hugpee/__init__.py
hugpee-0.1.1.dist-info/LICENSE
hugpee-0.1.1.dist-info/METADATA
hugpee-0.1.1.dist-info/WHEEL
hugpee-0.1.1.dist-info/top_level.txt
hugpee-0.1.1.dist-info/RECORD
