Metadata-Version: 2.1
Name: hugpee
Version: 0.1.1
Summary: A Python module which simplifies the creation of RESTful CRUD endpoints in hug, for peewee models.
Home-page: https://github.com/kostasdizas/hugpee
Author: Kostas Dizas
Author-email: kdizas@gmail.com
License: MIT
Platform: UNKNOWN
Requires: hug
Requires: peewee
